odoo/addons/shipment_advice/README.rst
odoo/addons/shipment_advice/__init__.py
odoo/addons/shipment_advice/__manifest__.py
odoo/addons/shipment_advice/data/ir_sequence.xml
odoo/addons/shipment_advice/demo/stock_dock.xml
odoo/addons/shipment_advice/i18n/it.po
odoo/addons/shipment_advice/i18n/shipment_advice.pot
odoo/addons/shipment_advice/models/__init__.py
odoo/addons/shipment_advice/models/res_company.py
odoo/addons/shipment_advice/models/res_config_settings.py
odoo/addons/shipment_advice/models/shipment_advice.py
odoo/addons/shipment_advice/models/stock_move.py
odoo/addons/shipment_advice/models/stock_move_line.py
odoo/addons/shipment_advice/models/stock_package_level.py
odoo/addons/shipment_advice/models/stock_picking.py
odoo/addons/shipment_advice/readme/CONTRIBUTORS.rst
odoo/addons/shipment_advice/readme/CREDITS.rst
odoo/addons/shipment_advice/readme/DESCRIPTION.rst
odoo/addons/shipment_advice/report/report_shipment_advice.xml
odoo/addons/shipment_advice/report/reports.xml
odoo/addons/shipment_advice/security/ir.model.access.csv
odoo/addons/shipment_advice/static/description/icon.png
odoo/addons/shipment_advice/static/description/index.html
odoo/addons/shipment_advice/tests/__init__.py
odoo/addons/shipment_advice/tests/common.py
odoo/addons/shipment_advice/tests/test_shipment_advice.py
odoo/addons/shipment_advice/tests/test_shipment_advice_auto_close.py
odoo/addons/shipment_advice/tests/test_shipment_advice_load.py
odoo/addons/shipment_advice/tests/test_shipment_advice_picking_values.py
odoo/addons/shipment_advice/tests/test_shipment_advice_plan.py
odoo/addons/shipment_advice/tests/test_shipment_advice_stock_user.py
odoo/addons/shipment_advice/tests/test_shipment_advice_to_load.py
odoo/addons/shipment_advice/tests/test_shipment_advice_unload.py
odoo/addons/shipment_advice/views/res_config_settings.xml
odoo/addons/shipment_advice/views/shipment_advice.xml
odoo/addons/shipment_advice/views/stock_move.xml
odoo/addons/shipment_advice/views/stock_move_line.xml
odoo14_addon_shipment_advice-14.0.2.6.0.dist-info/METADATA
odoo14_addon_shipment_advice-14.0.2.6.0.dist-info/WHEEL
odoo14_addon_shipment_advice-14.0.2.6.0.dist-info/top_level.txt
odoo14_addon_shipment_advice-14.0.2.6.0.dist-info/RECORD
